wdict/__init__.py
wdict/core.py
wdict-0.3.1.dist-info/LICENSE.txt
wdict-0.3.1.dist-info/METADATA
wdict-0.3.1.dist-info/WHEEL
wdict-0.3.1.dist-info/top_level.txt
wdict-0.3.1.dist-info/RECORD
