Metadata-Version: 2.1
Name: wdict
Version: 0.3.1
Summary: extended dictionary class
Home-page: https://github.com/shinaji/wdict
Author: shinaji
Author-email: shina.synergy@gmail.com
License: MIT
Keywords: dict
Platform: UNKNOWN
Classifier: License :: OSI Approved :: MIT License
Classifier: Intended Audience :: Developers
Classifier: Intended Audience :: Science/Research
Classifier: Development Status :: 4 - Beta
Classifier: Programming Language :: Python :: 3.6
Classifier: Programming Language :: Python :: 3.7
Classifier: Operating System :: OS Independent
Classifier: Topic :: Software Development
Requires-Dist: numpy
